purple_violin/__init__.py
purple_violin-0.0.3.dist-info/licenses/LICENSE.txt
purple_violin-0.0.3.dist-info/METADATA
purple_violin-0.0.3.dist-info/WHEEL
purple_violin-0.0.3.dist-info/top_level.txt
purple_violin-0.0.3.dist-info/RECORD
