Metadata-Version: 2.4
Name: purple-violin
Version: 0.0.3
Summary: My example purple violin
Author-email: Shimon Pats <shimon@example.com>
Maintainer-email: Shimon Pats <shimon@example.com>
License: Copyright 2025 purple-violin
Project-URL: Homepage, https://github.com/purple-training/violin
Project-URL: Bug Reports, https://github.com/purple-training/violin/issues
Project-URL: Source, https://github.com/purple-training/violin
Keywords: sample,setuptools,development
Classifier: Development Status :: 3 - Alpha
Classifier: Intended Audience :: Developers
Classifier: Topic :: Software Development :: Build Tools
Classifier: License :: OSI Approved :: MIT License
Classifier: Programming Language :: Python :: 3
Classifier: Programming Language :: Python :: 3.9
Classifier: Programming Language :: Python :: 3.10
Classifier: Programming Language :: Python :: 3.11
Classifier: Programming Language :: Python :: 3.12
Classifier: Programming Language :: Python :: 3.13
Classifier: Programming Language :: Python :: 3 :: Only
Requires-Python: >=3.9
License-File: LICENSE.txt
Dynamic: license-file
